ealib/__init__.py
ealib/main.py
ealib/functions/__init__.py
ealib/functions/noise.py
ealib/functions/unconstrained.py
ealib/minimizers/__init__.py
ealib/minimizers/cem.py
ealib/minimizers/cmaes.py
ealib/minimizers/ga.py
ealib/minimizers/optimizer.py
ealib/minimizers/pso.py
ealib/minimizers/randomsearch.py
ealib/minimizers/saes11.py
ealib/utils/__init__.py
ealib/utils/plot.py
ealib-0.4.0.dist-info/AUTHORS
ealib-0.4.0.dist-info/LICENSE
ealib-0.4.0.dist-info/METADATA
ealib-0.4.0.dist-info/WHEEL
ealib-0.4.0.dist-info/top_level.txt
ealib-0.4.0.dist-info/RECORD
