Metadata-Version: 2.1
Name: ealib
Version: 0.4.0
Summary: An open source Python library for mathematical optimization
Author-email: Jérémie DECOCK <jd.jdhp@gmail.com>
Classifier: Development Status :: 4 - Beta
Classifier: Intended Audience :: Developers
Classifier: Natural Language :: English
Classifier: Operating System :: OS Independent
Classifier: Programming Language :: Python :: 3
Classifier: Topic :: Software Development :: Libraries
Requires-Python: >=3.11
License-File: LICENSE
License-File: AUTHORS
Requires-Dist: numpy
Requires-Dist: pandas
Requires-Dist: scipy
